pyfrazao/__init__.py
pyfrazao/main.py
pyfrazao-1.0.dist-info/METADATA
pyfrazao-1.0.dist-info/WHEEL
pyfrazao-1.0.dist-info/top_level.txt
pyfrazao-1.0.dist-info/RECORD
