Metadata-Version: 2.1
Name: pyfrazao
Version: 1.0
Summary: This package was made with pip-boilerplate
Home-page: https://github.com/victorcmoura/pip-boilerplate
Author: Victor Moura
Author-email: victor_cmoura@hotmail.com
License: GPL-3.0
Platform: UNKNOWN
